a_pandas_ex_sequence_search/README.MD
a_pandas_ex_sequence_search/__init__.py
a_pandas_ex_sequence_search/requirements.txt
a_pandas_ex_sequence_search/thirdparty.json
a_pandas_ex_sequence_search-0.10.dist-info/LICENSE.rst
a_pandas_ex_sequence_search-0.10.dist-info/METADATA
a_pandas_ex_sequence_search-0.10.dist-info/WHEEL
a_pandas_ex_sequence_search-0.10.dist-info/top_level.txt
a_pandas_ex_sequence_search-0.10.dist-info/RECORD
