Metadata-Version: 2.1
Name: a-pandas-ex-sequence-search
Version: 0.10
Summary: Sequence / string search with NumPy in pandas DataFrames
Home-page: https://github.com/hansalemaos/a_pandas_ex_sequence_search
Author: Johannes Fischer
Author-email: aulasparticularesdealemaosp@gmail.com
License: MIT
Keywords: sequence,search,string,numpy
Classifier: Development Status :: 4 - Beta
Classifier: Programming Language :: Python :: 3 :: Only
Classifier: Programming Language :: Python :: 3.10
Classifier: Topic :: Software Development :: Libraries :: Python Modules
Classifier: Topic :: Utilities
License-File: LICENSE.rst
Requires-Dist: a-pandas-ex-apply-ignore-exceptions
Requires-Dist: npsearchsequence
Requires-Dist: pandas
